ldap/__init__.py
ldap/mock.py
ldap/server.py
ldap-1.0.2.dist-info/DESCRIPTION.rst
ldap-1.0.2.dist-info/LICENSE.txt
ldap-1.0.2.dist-info/METADATA
ldap-1.0.2.dist-info/RECORD
ldap-1.0.2.dist-info/WHEEL
ldap-1.0.2.dist-info/entry_points.txt
ldap-1.0.2.dist-info/metadata.json
ldap-1.0.2.dist-info/top_level.txt
